eeve/__init__.py
eeve/__main__.py
eeve/base_classes.py
eeve/database.py
eeve/eeve actions/activity_logger.py
eeve/eeve actions/changePowerPlan.py
eeve/eeve actions/eeve_GUI/__init__.py
eeve/eeve actions/eeve_GUI/__main__.py
eeve/eeve actions/eeve_GUI/Controllers/EditActionController.py
eeve/eeve actions/eeve_GUI/Controllers/EditEventController.py
eeve/eeve actions/eeve_GUI/Controllers/EditTriggerController.py
eeve/eeve actions/eeve_GUI/Controllers/EventsController.py
eeve/eeve actions/eeve_GUI/Controllers/LoginController.py
eeve/eeve actions/eeve_GUI/style.py
eeve/eeve actions/eeve_GUI/Views/EditAction.qml
eeve/eeve actions/eeve_GUI/Views/EditEvent.qml
eeve/eeve actions/eeve_GUI/Views/EditTrigger.qml
eeve/eeve actions/eeve_GUI/Views/Events.qml
eeve/eeve actions/eeve_GUI/Views/FileDialog.py
eeve/eeve actions/eeve_GUI/Views/list-delete.png
eeve/eeve actions/eeve_GUI/Views/Login.qml
eeve/eeve actions/eeve_GUI/Views/main.qml
eeve/eeve actions/eeve_GUI/Views/open-file.png
eeve/eeve actions/eeve_GUI/Views/PressAndHoldButton.qml
eeve/eeve actions/if_action.py
eeve/eeve actions/list_dir.py
eeve/eeve actions/play_audio.py
eeve/eeve actions/python_loader.py
eeve/eeve actions/random_actions.py
eeve/eeve actions/REST_request.py
eeve/eeve actions/run.py
eeve/eeve actions/set_var.py
eeve/eeve actions/start_process.py
eeve/eeve actions/test_action.py
eeve/eeve actions/wait_action.py
eeve/eeve events.txt
eeve/eeve eventsssss.txt
eeve/eeve plugins/open_web_page.py
eeve/eeve plugins/tp-interface.py
eeve/eeve plugins/win_key_hook/__init__.py
eeve/eeve plugins/win_key_hook/__main__.py
eeve/eeve plugins/win_key_hook/input_parser.py
eeve/eeve plugins/win_key_hook/key_map.py
eeve/eeve triggers/broadcastCatcher.py
eeve/eeve triggers/on_start.py
eeve/eeve triggers/rawinput.py
eeve/eeve triggers/structs.py
eeve/eeve triggers/timer_trigger.py
eeve/eeve.py
eeve/helpers.py
eeve/importer.py
eeve/mappings.py
eeve/taskinfo.py
eeve/ts.py
eeve/variable.py
eeve/wrapper.py
eeve-1.6.1.dist-info/LICENSE
eeve-1.6.1.dist-info/WHEEL
eeve-1.6.1.dist-info/METADATA
eeve-1.6.1.dist-info/RECORD
