Metadata-Version: 2.1
Name: eeve
Version: 1.6.1
Summary: A flexible, powerfull and simple event trigger
Home-page: https://github.com/vMarcelino/eeve
License: Apache-2.0
Author: Victor Marcelino
Author-email: victor.fmarcelino@gmail.com
Requires-Python: >=3.6
Classifier: License :: OSI Approved :: Apache Software License
Classifier: Programming Language :: Python :: 3
Classifier: Programming Language :: Python :: 3.6
Classifier: Programming Language :: Python :: 3.7
Requires-Dist: travel-backpack (>=0.12.0)
